setup.py
camel/__init__.py
camel/camel.py
camel/version.py
camel/helper/bloomfilter.py
camel/helper/common.py
camel/modules/__init__.py
camel/modules/annotate.py
camel/modules/average.py
camel/modules/call.py
camel/modules/cluster.py
camel/modules/convert.py
camel/modules/dmr.py
camel/modules/index.py
camel/modules/merge.py
camel/modules/meta.py
camel/modules/nome_plot.py
camel/modules/nome_plot2.py
camel/modules/pca.py
camel/modules/statistics.py
camel/modules/stats_coverage.py
camel/modules/view.py
camel/wrap/region.py
camel/wrap/sample.py
gi_camel.egg-info/PKG-INFO
gi_camel.egg-info/SOURCES.txt
gi_camel.egg-info/dependency_links.txt
gi_camel.egg-info/entry_points.txt
gi_camel.egg-info/not-zip-safe
gi_camel.egg-info/requires.txt
gi_camel.egg-info/top_level.txt