Metadata-Version: 1.1
Name: gi-camel
Version: 0.4.5
Summary: camel is a tool for calling and analysing CpG and GpC methylation values
Home-page: https://bitbucket.org/christopherschroeder/camel
Author: Christopher Schröder and Sven Rahmann
Author-email: christopher.schroeder@tu-dortmund.de, sven.rahmann@uni-due.de
License: MIT
Platform: UNKNOWN
Classifier: Development Status :: 5 - Production/Stable
Classifier: Environment :: Console
Classifier: Intended Audience :: Science/Research
Classifier: License :: OSI Approved :: MIT License
Classifier: Natural Language :: English
Classifier: Programming Language :: Python :: 3
Classifier: Topic :: Scientific/Engineering :: Bio-Informatics
